starvell/__init__.py
starvell/account.py
starvell/session.py
starvell/socket.py
starvell/enums/__init__.py
starvell/enums/enums.py
starvell/errors/__init__.py
starvell/errors/exceptions.py
starvell/events/__init__.py
starvell/events/events.py
starvell/filters/__init__.py
starvell/filters/filters.py
starvell/propertys/__init__.py
starvell/propertys/my_profile.py
starvell/types/__init__.py
starvell/types/chats.py
starvell/types/exchange_rate.py
starvell/types/messages.py
starvell/types/offer.py
starvell/types/order.py
starvell/types/review.py
starvell/types/table.py
starvell/types/user.py
starvell/utils/__init__.py
starvell/utils/utils.py
starvell-0.0.1.dist-info/METADATA
starvell-0.0.1.dist-info/WHEEL
starvell-0.0.1.dist-info/top_level.txt
starvell-0.0.1.dist-info/RECORD
