Metadata-Version: 2.4
Name: starvell
Version: 0.0.1
Summary: библиотека для взаимодействия с API сайта Starvell
Author-email: Mark <kash1d@gmail.com>
License: MIT
Project-URL: Homepage, https://github.com/kash1dd/StarvellSDK
Project-URL: Issues, https://github.com/kash1dd/StarvellSDK/issues
Keywords: starvell,api,library,bot,tools
Classifier: Programming Language :: Python :: 3
Classifier: License :: OSI Approved :: MIT License
Classifier: Operating System :: OS Independent
Requires-Python: >=3.10
Requires-Dist: pydantic>=2.11.10
Requires-Dist: requests>=2.32.5
Requires-Dist: ruff>=0.13.3
Requires-Dist: setuptools>=61.0
Requires-Dist: websocket-client>=1.8.0
